[
    {
        "Instrument": "Fife",
        "MannequinTag": "InstrumentFife",
        "StartPrefix": "Play_Instru_Tone_",
        "StopPrefix": "Stop_Instru_Tone_",
        "SingleNoteOnly": false,
        "ShowAdvancedMenu": true
    },
    {
        "Instrument": "Snare",
        "MannequinTag": "InstrumentSnare",
        "StartPrefix": "Play_Instru_Snare",
        "StopPrefix": "Stop_Instru_Snare",
        "SingleNoteOnly": true,
        "ShowAdvancedMenu": true
    },
    {
        "Instrument": "WarHorn",
        "MannequinTag": "InstrumentWarHorn",
        "StartPrefix": "Play_Instru_WarHorn",
        "StopPrefix": "Stop_Instru_WarHorn",
        "SingleNoteOnly": true,
        "ShowAdvancedMenu": false
    }
]