[
    {
        "CategoryId": "Boss",
        "CategoryDamageMod": 2.0999999046325684,
        "CategoryHealthMod": 40,
        "CategoryDropChanceMod": 1
    },
    {
        "CategoryId": "Boss-",
        "CategoryDamageMod": 1.899999976158142,
        "CategoryHealthMod": 25,
        "CategoryDropChanceMod": 1
    },
    {
        "CategoryId": "Boss+",
        "CategoryDamageMod": 2.5,
        "CategoryHealthMod": 50,
        "CategoryDropChanceMod": 1
    },
    {
        "CategoryId": "Critter",
        "CategoryDamageMod": 0.05000000074505806,
        "CategoryHealthMod": 0.05000000074505806,
        "CategoryDropChanceMod": 0
    },
    {
        "CategoryId": "Dungeon",
        "CategoryDamageMod": 1.7000000476837158,
        "CategoryHealthMod": 4,
        "CategoryDropChanceMod": 0.10000000149011612
    },
    {
        "CategoryId": "Dungeon-",
        "CategoryDamageMod": 1.350000023841858,
        "CategoryHealthMod": 2,
        "CategoryDropChanceMod": 0.05000000074505806
    },
    {
        "CategoryId": "Dungeon+",
        "CategoryDamageMod": 2.049999952316284,
        "CategoryHealthMod": 10,
        "CategoryDropChanceMod": 0.15000000596046448
    },
    {
        "CategoryId": "DungeonBoss",
        "CategoryDamageMod": 2.5,
        "CategoryHealthMod": 50,
        "CategoryDropChanceMod": 1
    },
    {
        "CategoryId": "DungeonMiniBoss",
        "CategoryDamageMod": 2.25,
        "CategoryHealthMod": 30,
        "CategoryDropChanceMod": 1
    },
    {
        "CategoryId": "Elite",
        "CategoryDamageMod": 1.399999976158142,
        "CategoryHealthMod": 3,
        "CategoryDropChanceMod": 0.15000000596046448
    },
    {
        "CategoryId": "Elite-",
        "CategoryDamageMod": 1.2000000476837158,
        "CategoryHealthMod": 1.7999999523162842,
        "CategoryDropChanceMod": 0.10000000149011612
    },
    {
        "CategoryId": "Elite+",
        "CategoryDamageMod": 1.7000000476837158,
        "CategoryHealthMod": 8,
        "CategoryDropChanceMod": 0.44999998807907104
    },
    {
        "CategoryId": "EliteMiniBoss",
        "CategoryDamageMod": 1.899999976158142,
        "CategoryHealthMod": 25,
        "CategoryDropChanceMod": 1
    },
    {
        "CategoryId": "EliteBoss",
        "CategoryDamageMod": 2.0999999046325684,
        "CategoryHealthMod": 40,
        "CategoryDropChanceMod": 1
    },
    {
        "CategoryId": "Named_Solo",
        "CategoryDamageMod": 1.2000000476837158,
        "CategoryHealthMod": 1.5,
        "CategoryDropChanceMod": 1
    },
    {
        "CategoryId": "Named_Solo+",
        "CategoryDamageMod": 1.2999999523162842,
        "CategoryHealthMod": 2.5,
        "CategoryDropChanceMod": 0.6499999761581421
    },
    {
        "CategoryId": "Solo",
        "CategoryDamageMod": 1,
        "CategoryHealthMod": 1,
        "CategoryDropChanceMod": 0.08500000089406967
    },
    {
        "CategoryId": "Solo-",
        "CategoryDamageMod": 0.6000000238418579,
        "CategoryHealthMod": 0.6000000238418579,
        "CategoryDropChanceMod": 0.05000000074505806
    },
    {
        "CategoryId": "Solo+",
        "CategoryDamageMod": 1.25,
        "CategoryHealthMod": 2,
        "CategoryDropChanceMod": 0.25
    },
    {
        "CategoryId": "OutpostRushSolo",
        "CategoryDamageMod": 1,
        "CategoryHealthMod": 1,
        "CategoryDropChanceMod": 1
    },
    {
        "CategoryId": "OutpostRushElite",
        "CategoryDamageMod": 1.25,
        "CategoryHealthMod": 2.75,
        "CategoryDropChanceMod": 1
    },
    {
        "CategoryId": "OutpostRushElite+",
        "CategoryDamageMod": 3,
        "CategoryHealthMod": 4.5,
        "CategoryDropChanceMod": 1
    },
    {
        "CategoryId": "Player",
        "CategoryDamageMod": 1,
        "CategoryHealthMod": 1,
        "CategoryDropChanceMod": 1
    }
]