<resources xmlns:xsi="http://www.w3.org/2001/XMLSchema-instance">
	<string key="ui_abandon">Abandonar esta casa</string>
	<string key="ui_beds">Camas</string>
	<string key="ui_fast_travel_mission_abandon_confirm">AVISO: Fazer uma Viagem Rápida fará você abandonar todas as missões da facção PvP.\n{count} missão será abandonada.\n\nContinuar?</string>
	<string key="ui_cannot_travel_in_war">Você não pode fazer uma viagem rápida enquanto estiver em guerra</string>
	<string key="ui_cannot_travel_encumbered">Você não pode fazer uma viagem rápida enquanto estiver sobrecarregado</string>
	<string key="ui_cannot_travel_dead">Você não poderá retornar nem fazer uma viagem rápida ao morrer.</string>
	<string key="ui_cannot_travel_currency">É necessário {coin} &lt;img src="lyshineui/images/icon_crown" xPadding="0" scale="1" yOffset="0.5"&gt;&lt;/img&gt; para fazer viagem rápida</string>
	<string key="ui_cannot_travel_currency_azoth">É necessário {coin} &lt;img src="lyshineui/images/icon_azoth" xPadding="0" scale="1" yOffset="0.5"&gt;&lt;/img&gt; para fazer viagem rápida</string>
	<string key="ui_cannot_reset_travel_currency">Pague {coin} &lt;img src="lyshineui/images/icon_azoth" xPadding="0" scale="1.5" yOffset="1"&gt;&lt;/img&gt; para reiniciar a recarga.</string>
	<string key="ui_cannot_travel_encounter">Você não pode fazer uma viagem rápida durante um confronto</string>
	<string key="ui_cannot_travel_outpost_rush">Você não pode fazer uma viagem rápida durante a Investida do Posto Avançado</string>
	<string key="ui_need_reset_travel_currency">Você precisa de {coin} &lt;img src="lyshineui/images/icon_azoth" xPadding="0" scale="1.5" yOffset="1"&gt;&lt;/img&gt; para reiniciar a recarga.</string>
	<string key="ui_reset_travel">Recarga de reinício de {coin} &lt;img src="lyshineui/images/icon_azoth" xPadding="0" scale="1" yOffset="0.5"&gt;&lt;/img&gt;</string>
	<string key="ui_cant_pay_property_tax">É possível pagar em {time}</string>
	<string key="ui_chairs">Cadeiras</string>
	<string key="ui_context_menu_hint">Opções</string>
	<string key="ui_currently_displaying">Exibido no momento ao público</string>
	<string key="ui_decoration_mode_unpaid">Impostos devem ser pagos para decorar sua casa.</string>
	<string key="ui_decorations">Decorações</string>
	<string key="ui_spirit_shrine">Santuário Espiritual</string>
	<string key="ui_spirit_shrine_desc">Faça uma viagem rápida para qualquer Assentamento, Posto Avançado ou Santuário Espiritual visitado anteriormente.</string>
	<string key="ui_fast_travel">Viagem Rápida</string>
	<string key="ui_fast_travel_channel">Viagem Rápida...</string>
	<string key="ui_fast_travel_popup_confirm">Quer fazer uma viagem rápida até este local?</string>
	<string key="ui_inn_recall_popup_confirm">Quer retornar a esta estalagem?</string>
	<string key="ui_inn_recall_from_esc_popup_confirm">Quer retornar à estalagem localizada em {territoryName}?</string>
	<string key="ui_watchtower_recall_from_esc_popup_confirm">Você gostaria de retornar à torre de vigia localizada em {territoryName}?</string>
	<string key="ui_house_recall_popup_confirm">Quer retornar à sua casa?</string>
	<string key="ui_fast_travel_reset_popup">Reiniciar recarga?</string>
	<string key="ui_fast_travel_reset_popup_confirm">Quer reiniciar a recarga?</string>
	<string key="ui_group_member_homes">Casas de Membros do Grupo</string>
	<string key="ui_group_member_homes_no_data">Não há membros do grupo vivendo neste lote.</string>
	<string key="ui_house">Casa</string>
	<string key="ui_house_abandon_notification">Sua casa {houseName} foi abandonada.</string>
	<string key="ui_house_abandon_popup_desc">Você já tem 1 casa nesta vila.\n Você gostaria de abandonar {houseName} para comprar esta casa?\nTodos os troféus e móveis da casa abandonada serão movidos para o Inventário da Vila.</string>
	<string key="ui_house_abandon_popup_title">Você só pode ter uma casa em cada vila.</string>
	<string key="ui_house_abandon_this_popup_desc">&lt;font color="#f25d5d"&gt;O custo da compra e os impostos não serão reembolsados se esta casa for abandonada.&lt;/font&gt;\nTodos os troféus e móveis da casa abandonada serão movidos para o Inventário da Vila.\n\nPara continuar, digite {territoryName} abaixo.</string>
	<string key="ui_house_abandon_this_house_desc">O custo da compra e os impostos não serão reembolsados se esta casa for abandonada. Todos os troféus e móveis da casa serão movidos para o inventário da vila.</string>
	<string key="ui_house_abandon_this_popup_title">Abandonar Casa?</string>
	<string key="ui_house_abandon_confirm_placeholder_text">Digite o nome do território.</string>
	<string key="ui_house_abandon_confirm_button">Abandonar Casa</string>
	<string key="ui_house_already_owned">Já Adquirida</string>
	<string key="ui_house_hint_decorate">Decorar</string>
	<string key="ui_house_hint_exit">Sair</string>
	<string key="ui_house_hint_menu">Menu</string>
	<string key="ui_house_hint_tips">Dicas</string>
	<string key="ui_house_hud_hint">Invisível para outros jogadores</string>
	<string key="ui_house_max_home_owned_on_territory">Máximo de Casas Adquiridas No Território</string>
	<string key="ui_house_menu">Gerenciar sua Casa</string>
	<string key="ui_house_preview">Pré-visualizar esta casa</string>
	<string key="ui_house_price">Preço da Casa</string>
	<string key="ui_house_property_tax_desc">{coin} &lt;img src="lyshineui/images/icon_crown" xPadding="0" scale="1" yOffset="0.5"&gt;&lt;/img&gt;</string>
	<string key="ui_house_property_tax_sub_desc">/ período de pagamento necessário para manter esta casa.</string>
	<string key="ui_house_purchase">Comprar esta casa {coinText}</string>
	<string key="ui_house_purchase_confirm_popup_title">Comprar Casa</string>
	<string key="ui_house_purchase_confirm_popup_desc">Quer comprar esta casa?</string>
	<string key="ui_house_purchase_confirm_popup_yes_button">Comprar</string>
	<string key="ui_house_purchase_confirm_popup_no_button">Cancelar</string>
	<string key="ui_house_purchase_error_unknown">Erro de compra desconhecido.</string>
	<string key="ui_house_purchase_error_full">Este lote está cheio. \nNão há unidade disponível para venda.</string>
	<string key="ui_house_purchase_error_standing">Esta casa requer nível {standingRank} de posição de Território em {standingName} para ser comprada.</string>
	<string key="ui_home_purchase_error_level_first">É preciso estar no nível {level} para comprar uma casa.</string>
	<string key="ui_home_purchase_error_level">É preciso estar no nível {level} para comprar a próxima casa.</string>
	<string key="ui_house_purchase_error_territory_bonus">Precisa de bônus de permissão de alojamento no território {standingName}</string>
	<string key="ui_house_purchase_error_territory_bonus_desc">&lt;font face="lyshineui/fonts/Nimbus_semibold.font" color="#F25D5D"&gt;Você não tem&lt;/font&gt; &lt;font face="lyshineui/fonts/Nimbus_semibold.font"&gt; Bônus de Propriedade da Casa &lt;/font&gt; &lt;font face="lyshineui/fonts/Nimbus_semibold.font" color="#F25D5D"&gt;neste território para comprar uma casa.&lt;/font&gt;\n &lt;font color="#AAAAAA"&gt;Bônus Titularidade da Casa disponível no&lt;/font&gt; &lt;font color="#EEEEEE"&gt; nível {standingRank} de Posição do Território.&lt;/font&gt;</string>
	<string key="ui_house_purchase_standing_requirement">Nível de Posição de {standingName}: {standingValue}</string>
	<string key="ui_house_purchase_standing_bonus_requirement">Bônus de Titularidade da Casa em {standingName}</string>
	<string key="ui_house_purchased">Casa comprada!</string>
	<string key="ui_house_purchased_detail">Parabéns, agora você é &lt;font color="#FFFFFF"&gt;proprietário de uma casa&lt;/font&gt; em &lt;font color="#F4D179"&gt;{settlementName}&lt;/font&gt;! Lembre-se de pagar os Impostos Imobiliários para usar os recursos de alojamento!</string>
	<string key="ui_house_tax_unpaid_flyout_warning">Casa desativada devido a impostos imobiliários não pagos.</string>
	<string key="ui_house_travel_cooldown_remaining">É possível fazer Viagem rápida novamente em {time}</string>
	<string key="ui_house_type">Tipo da Casa</string>
	<string key="ui_house_unpaid_taxes">Quantia Devida</string>
	<string key="ui_house_unpaid_taxes_string">Sua Casa (Desativada)</string>
	<string key="ui_house_tax">Imposto Imobiliário</string>
	<string key="ui_house_unpaid_taxes_due_soon">Imposto Imobiliário de {territoryName} em: {time}. Pague o imposto para continuar fazendo viagens rápidas e decorações.</string>
	<string key="ui_house_overdue_at">Imposto de {territoryName} Vencido. Pague o imposto para continuar fazendo viagens rápidas e decorações.</string>
	<string key="ui_house_overdue_label">Imposto Vencido</string>
	<string key="ui_house_overdue_desc">O imposto imobiliário está vencido. Pague o imposto para ativar os recursos de alojamento.</string>
	<string key="ui_housing_cant_afford">Você precisa de mais moedas para comprar esta casa.</string>
	<string key="ui_housing_decorate">Decorar</string>
	<string key="ui_housing_decorate_desc">Posicione Mobília e Animais de Estimação</string>
	<string key="ui_housing_disabled">Desativada</string>
	<string key="ui_housing_disabled_tooltip">Sua Casa está desativada. Pague os impostos agora para reativar sua casa!</string>
	<string key="ui_housing_enabled">Ativada</string>
	<string key="ui_housing_fast_travel">Viagem Rápida</string>
	<string key="ui_housing_fast_travel_desc">De qualquer lugar, para o seu lar</string>
	<string key="ui_housing_decorations">Modo Decoração</string>
	<string key="ui_housing_features">Recursos de Alojamento</string>
	<string key="ui_housing_grid_snap_hint">Posicionamento na Grade</string>
	<string key="ui_housing_hide_ui">Ocultar</string>
	<string key="ui_housing_item_count">Decorações Colocadas</string>
	<string key="ui_housing_item_score">Pontuação de Decoração</string>
	<string key="ui_housing_next_due_in">Próximo Pagamento em</string>
	<string key="ui_housing_surface_lock_hint">Fixar na Superfície</string>
	<string key="ui_housing_owned_filter">Mostrar somente os itens adquiridos</string>
	<string key="ui_housing_pay_taxes">Pagar Imposto</string>
	<string key="ui_housing_no_items_found">Nenhum</string>
	<string key="ui_housing_object">Objeto de Alojamento</string>
	<string key="ui_housing_point_tooltip">As 20 casas com pontuação da casa mais altas são atualizadas nesta lista a cada 2 dias.\n\nA pontuação da casa é calculada com base nos ganhos do jogador de Posição do Território e os móveis colocados na propriedade.</string>
	<string key="ui_housing_purchase_house">Comprar esta Casa</string>
	<string key="ui_housing_rotate_camera_hint">&lt;img src="lyshineui/images/icons/misc/Icon_RightMouseButton" xPadding="0" scale="2.2" yOffset="8"&gt;&lt;/img&gt; Rotacionar Câmera</string>
	<string key="ui_housing_rotate_object_hint">Rotacionar Objeto</string>
	<string key="ui_housing_select_house">Selecionar uma casa para visualizar</string>
	<string key="ui_housing_time_calculating">Calculando...</string>
	<string key="ui_housing_time_to_recompute">Esta lista será atualizada em &lt;font color="#ffffff"&gt;{time}&lt;/font&gt;</string>
	<string key="ui_housing_trophy_buff">Buff de Troféus</string>
	<string key="ui_housing_trophy_buffs">Buffs de Troféus</string>
	<string key="ui_housing_trophy_buffs_disabled">Buffs de Troféus (Desativados)</string>
	<string key="ui_housing_trophy_buff_desc">Posicione troféus que concedem buffs</string>
	<string key="ui_housing_trophy_buff_desc_tooltip">Um troféu que te inspira quando colocado em sua casa.</string>
	<string key="ui_housing_trophy_empty_slot">Espaço de Troféu Vazio</string>
	<string key="ui_housing_update_time">Esta lista será atualizada em {time}</string>
	<string key="ui_lighting">Iluminação</string>
	<string key="ui_max_homes_owned">Máximo de Casas Adquiridas</string>
	<string key="ui_max_homes_owned_territory">Máximo de Casas Adquiridas Neste Território</string>
	<string key="ui_misc">Diversos</string>
	<string key="ui_my_house_map_desc">{location} casa {number}</string>
	<string key="ui_my_house_map_desc_disabled">{location} casa {number} (Desativado)</string>
	<string key="ui_my_house_map_title">Sua Casa</string>
	<string key="ui_my_houses_map_title">Suas Casas</string>
	<string key="ui_pay_property_tax_desc">Pague o Imposto Imobiliário usando o mapa ou quando estiver na sua casa.</string>
	<string key="ui_no_home_owners">Casa Vazia</string>
	<string key="ui_num_housing_points">{points} Pontos</string>
	<string key="ui_owner_list">Lista do Proprietário</string>
	<string key="ui_pay_house_tax_fail">Erro ao pagar impostos em casa. Tente novamente.</string>
	<string key="ui_pay_property_tax">Pague Impostos Imobiliários</string>
	<string key="ui_pay_property_tax_popup_desc">É preciso pagar os impostos imobiliários para retornar à sua casa, renascer na sua casa e decorar sua casa.\nOs impostos estão previstos para {firstCycle} após a compra de uma casa e a cada {otherCycle} subsequente.</string>
	<string key="ui_property_tax">Impostos Imob.</string>
	<string key="ui_property_tax_amount_desc">Imposto Imobiliário Periódico</string>
	<string key="ui_property_tax_desc">Pague Impostos Imobiliários periódicos para continuar usando os recursos de alojamento.</string>
	<string key="ui_property_tax_due">Valor Devido</string>
	<string key="ui_property_tax_success_desc">Você pagou com êxito o Imposto Imobiliário da sua casa.</string>
	<string key="ui_residence">Residência de {playerName}</string>
	<string key="ui_resident_homes_already_showing_current">Vazio</string>
	<string key="ui_resident_homes_no_data">Não há nenhum outro jogador vivendo neste lote no momento.</string>
	<string key="ui_reward_type_community_goal_territory_standing">{amount} Posição do Território</string>
	<string key="ui_shelves">Prateleiras</string>
	<string key="ui_start_move_housing_item">Mover Item</string>
	<string key="ui_top_houses">Melhores &lt;font face="lyshineui/fonts/CaslonAnt.font"&gt;20&lt;/font&gt; Casas</string>
	<string key="ui_tables">Mesas</string>
	<string key="ui_trophies">Troféus</string>
	<string key="ui_pets">Animais</string>
	<string key="ui_vegetation">Vegetação</string>
	<string key="ui_your_house">Sua Casa</string>
	<string key="ui_your_house_disabled">Sua Casa (Desativada)</string>
	<string key="ui_recall_to_house">Retornar à casa</string>
	<string key="ui_recall_to_house_disabled">Retornar à casa (desativada)</string>
	<string key="ui_housingDecResult_Unknown">Erro de posicionamento desconhecido</string>
	<string key="ui_housingDecResult_NotOwner">Não é possível posicionar, a casa não é sua</string>
	<string key="ui_housingDecResult_NoItemSelected">Não é possível posicionar, nenhum item</string>
	<string key="ui_housingDecResult_InvalidItem">Não é possível posicionar, item inválido</string>
	<string key="ui_housingDecResult_InvalidPosition">Não é possível posicionar, posição inválida</string>
	<string key="ui_housingDecResult_ItemIdLimit">Não é possível posicionar, o limite foi alcançado para este item</string>
	<string key="ui_housingDecResult_Waiting">Não é possível posicionar, aguardando</string>
	<string key="ui_housingDecResult_TimeOut">Não é possível posicionar, tempo limite esgotado</string>
	<string key="ui_housingDecResult_ItemLimit">Não é possível posicionar, muitos itens</string>
	<string key="ui_housingDecResult_TagLimit">Não é possível posicionar, muitos itens deste tipo</string>
	<string key="ui_housingDecResult_entitlementLimit">Não é possível posicionar, muitos itens deste tipo</string>
	<string key="ui_inn_checked_in">{territoryName} é o seu novo ponto de retorno.</string>
	<string key="ui_active_home_point_fail">Falha ao dar entrada</string>
	<string key="ui_inn_fast_travel">Retornar à Estalagem</string>
	<string key="ui_watchtower_fast_travel">Retornar à Torre de Vigia</string>
	<string key="ui_inn_fast_travel_notavailable">Pode Retornar em: {time}</string>
	<string key="ui_inn">Estalagem</string>
	<string key="ui_inn_header">Estalagem {territoryName}.</string>
	<string key="ui_your_inn">&lt;font color="#73b651"&gt;&lt;font face="lyshineui/fonts/Nimbus_bold.font"&gt;Deu entrada&lt;/font&gt;&lt;/font&gt;\nEstalagem ativa. Você pode retornar e renascer nesta estalagem esteja onde estiver.</string>
	<string key="ui_inn_map_tooltip">&lt;font color="#949494"&gt;&lt;font face="lyshineui/fonts/Nimbus_bold.font"&gt;Não deu entrada&lt;/font&gt;&lt;/font&gt;\nDê entrada na estalagem para definir um ponto de retorno e renascimento.</string>
	<string key="ui_inn_check_in">Deu entrada na Estalagem {territoryName}.</string>
	<string key="ui_inn_check_in_desc">&lt;font color="#ffffff"&gt;&lt;font face="lyshineui/fonts/Nimbus_semibold.font"&gt;Bem-vindo(a) à Estalagem {territoryName}!&lt;/font&gt;&lt;/font&gt;\n\n Gostaria de &lt;font color="#f3d981"&gt;&lt;font face="lyshineui/fonts/Nimbus_semibold.font"&gt;dar entrada&lt;/font&gt;&lt;/font&gt;?\n\nFaça isso para retornar e renascer neste assentamento\nesteja onde estiver!</string>
	<string key="ui_inn_replace_desc">&lt;font color="#ffffff"&gt;&lt;font face="lyshineui/fonts/Nimbus_semibold.font"&gt;Bem-vindo(a) à Estalagem {territoryName}!&lt;/font&gt;&lt;/font&gt;\n\n Gostaria de &lt;font color="#f3d981"&gt;&lt;font face="lyshineui/fonts/Nimbus_semibold.font"&gt;dar entrada&lt;/font&gt;&lt;/font&gt;?\nFaça isso para retornar e renascer neste assentamento\nesteja onde estiver!\n\n&lt;font color="#f3d981"&gt;O ponto de retorno atual será substituído.&lt;/font&gt;</string>
	<string key="ui_current_inn_label">SUA ESTALAGEM ATUAL</string>
	<string key="ui_inn_already_checked_in">Ah, parece que você já deu entrada nesta estalagem!\n\nVocê pode retornar e renascer neste assentamento\nesteja onde estiver!</string>
	<string key="ui_current_inn_and_distance">Estalagem {territoryName} ({distance})</string>
	<string key="ui_recall_to">Retornar a</string>
	<string key="ui_fast_travel_to">Viagem Rápida até</string>
	<string key="ui_settlement_fast_travel">Viagem Rápida</string>
	<string key="ui_town_center">Centro da Vila</string>
	<string key="ui_settlement_fast_travel_desc">Faça uma Viagem Rápida até este Assentamento por {cost} &lt;img src="lyshineui/images/icon_azoth" xPadding="0" scale="1" yOffset="0.5"&gt;&lt;/img&gt;</string>
	<string key="ui_fast_travel_cost">{total} &lt;font color="#949494"&gt;/ {cost}&lt;/font&gt;</string>
	<string key="ui_cantfasttravel">Não é Possível Fazer a Viagem Rápida</string>
	<string key="ui_fast_travel_failed">Falha na Viagem Rápida</string>
	<string key="ui_cantrecall">Não é Possível Retornar</string>
	<string key="ui_fast_travel_error_inCooldown">{time}</string>
	<string key="ui_fast_travel_error_description_inCooldown">Esta ação está em recarga.</string>
	<string key="ui_fast_travel_error_description_inCooldown_with_time">Esta ação está em recarga.\nVocê pode retornar em {time}.</string>
	<string key="ui_fast_travel_error_noDestination">Você precisa visitar o assentamento antes de fazer uma viagem rápida até lá.</string>
	<string key="ui_fast_travel_error_noDestination_outpost">Você precisa visitar o posto avançado antes de fazer uma viagem rápida até lá.</string>
	<string key="ui_fast_travel_error_badStartLoc">Você só pode realizar uma viagem rápida em um assentamento, posto avançado ou santuário espiritual.</string>
	<string key="ui_fast_travel_error_cantAfford">Você não tem Azoth suficiente.</string>
	<string key="ui_fast_travel_error_encumbered">Você não pode fazer uma viagem rápida quando estiver com sobrecarga.</string>
	<string key="ui_recall_not_available_server_error">Não foi possível retornar devido a um erro de servidor.</string>
	<string key="ui_not_checked_in">Dê entrada na estalagem para ativar o ponto de retorno deste assentamento.</string>
	<string key="ui_not_checked_in_outpost">Dê entrada na estalagem para ativar o ponto de retorno deste posto avançado.</string>
	<string key="ui_not_checked_in_escape_menu">Dê entrada na estalagem para ativar um ponto de retorno.</string>
	<string key="ui_this_location">Este local</string>
	<string key="ui_travel">Viagem</string>
	<string key="ui_your_house_desc">Você sempre pode retornar e renascer na sua casa, desde que os impostos tenham sido pagos.</string>
	<string key="ui_view_warinfo">Ver Informações da Guerra</string>
	<string key="ui_view_taxinfo">Detalhes do Assentamento/Informação da Guerra</string>
	<string key="ui_view_personalstorage">Meu Armazém</string>
	<string key="ui_more_info">Mais informações</string>
	<string key="ui_company_discount">- ({discountPercent}%) por sua Companhia</string>
	<string key="@ui_house_refunded_title">Casa reembolsada</string>
	<string key="@ui_house_refunded_message">Devido a mudanças em {settlement}, sua casa foi reembolsada. Você recebeu {cost} &lt;img src="lyshineui/images/icon_crown" xPadding="0" scale="1" yOffset="0.5"&gt;&lt;/img&gt; e todos os itens de volta.</string>
	<string key="@ui_house_items_refunded_title">Itens de Casa reembolsados</string>
	<string key="@ui_house_items_refunded_single_message">Devido a mudanças em {settlement}, um item de casa foi devolvido ao seu inventário.</string>
	<string key="@ui_house_items_refunded_multiple_message">Devido a mudanças em {settlement}, {count} itens de casa foram devolvidos ao seu inventário.</string>
	<string key="ui_house_compensation_title">Compensação de Alojamento</string>
	<string key="ui_house_compensation_message_JAV141577">Devido a mensagens incorretas sobre o imposto para jogadores que comprarem sua primeira casa, você ganhou {amount} &lt;img src="lyshineui/images/icon_crown" xPadding="0" scale="1" yOffset="0.5"&gt;&lt;/img&gt; como um proprietário de casa. Esperamos que você continue curtindo New World e sua casa.</string>
	<string key="ui_house_type_items">Itens</string>
	<string key="ui_house_placed_items">Colocado(s)</string>
	<string key="ui_house_type_items_limits">Máximo de {numPets} {petPluralOrSingle}, {numLights} {lightPluralOrSingle} e {numStorage} {storagePluralOrSingle}.</string>
	<string key="ui_house_type_pet_singular">animal de estimação</string>
	<string key="ui_house_type_pet_plural">animais de estimação</string>
	<string key="ui_house_type_light_singular">luz</string>
	<string key="ui_house_type_light_plural">luzes</string>
	<string key="ui_house_type_storage_chest_singular">baú de armazenamento</string>
	<string key="ui_house_type_storage_chest_plural">baús de armazenamento</string>
	<string key="ui_house_type_cooldown">Recarga</string>
	<string key="ui_house_type_trophies">Espaços de Troféu</string>
	<string key="ui_house_all_placed_category">Todos os itens nesta casa</string>
	<string key="ui_housing_return_all_items">Devolver todos os itens para o armazenamento</string>
	<string key="ui_housing_return_all_items_popup_header">Devolver todos os itens?</string>
	<string key="ui_housing_return_all_items_popup_description">Tem certeza de que deseja remover todos os itens colocados nesta casa? Todos os itens serão devolvidos ao seu armazenamento.</string>
	<string key="ui_housing_no_placed_items_found">Nenhum item colocado</string>
	<string key="ui_locate_item">Localizar item</string>
	<string key="ui_return_to_storage">Devolver para o armazenamento</string>
	<string key="ui_house_lost_restored_message">Identificamos que sua casa foi perdida devido a um problema como o jogo. Sua casa em {settlement} foi recuperada.</string>
	<string key="ui_house_lost_restored_title">Casa restaurada</string>
	<string key="ui_house_lost_refunded_message">Identificamos que sua casa foi perdida devido a um problema como o jogo. Sua casa em {settlement} foi restituída e os móveis foram devolvidos ao seu depósito.</string>
	<string key="ui_house_lost_refunded_title">Casa reembolsada</string>
</resources>

