[
    {
        "ContributionId": "Spawn_Killed",
        "Category": "default",
        "Value": 100,
        "Shared": false,
        "Expires": false
    },
    {
        "ContributionId": "Spawn_Killed : Invasion_Grunt",
        "Category": "default",
        "Value": 100,
        "Shared": false,
        "Expires": false
    },
    {
        "ContributionId": "Spawn_Killed : Invasion_Bomber",
        "Category": "default",
        "Value": 150,
        "Shared": false,
        "Expires": false
    },
    {
        "ContributionId": "Spawn_Killed : Invasion_Sniper",
        "Category": "default",
        "Value": 150,
        "Shared": false,
        "Expires": false
    },
    {
        "ContributionId": "Spawn_Killed : Invasion_Spearman",
        "Category": "default",
        "Value": 200,
        "Shared": false,
        "Expires": false
    },
    {
        "ContributionId": "Spawn_Killed : Invasion_Swordsman",
        "Category": "default",
        "Value": 200,
        "Shared": false,
        "Expires": false
    },
    {
        "ContributionId": "Spawn_Killed : Invasion_Brute",
        "Category": "default",
        "Value": 500,
        "Shared": false,
        "Expires": false
    },
    {
        "ContributionId": "Spawn_Killed : Invasion_FireCannon",
        "Category": "default",
        "Value": 500,
        "Shared": false,
        "Expires": false
    },
    {
        "ContributionId": "Spawn_Killed : Invasion_CowLauncher",
        "Category": "default",
        "Value": 500,
        "Shared": false,
        "Expires": false
    },
    {
        "ContributionId": "Spawn_Killed : Invasion_Commander",
        "Category": "default",
        "Value": 750,
        "Shared": false,
        "Expires": false
    },
    {
        "ContributionId": "Spawn_Killed : Invasion_Priest",
        "Category": "default",
        "Value": 750,
        "Shared": false,
        "Expires": false
    },
    {
        "ContributionId": "Spawn_Killed : Invasion_Bear",
        "Category": "default",
        "Value": 750,
        "Shared": false,
        "Expires": false
    },
    {
        "ContributionId": "Wave_Started:1",
        "Category": "default",
        "Value": 1,
        "Shared": false,
        "Expires": false
    },
    {
        "ContributionId": "Wave_Started:2",
        "Category": "default",
        "Value": 500,
        "Shared": false,
        "Expires": false
    },
    {
        "ContributionId": "Wave_Started:3",
        "Category": "default",
        "Value": 1000,
        "Shared": false,
        "Expires": false
    },
    {
        "ContributionId": "Wave_Started:4",
        "Category": "default",
        "Value": 2000,
        "Shared": false,
        "Expires": false
    },
    {
        "ContributionId": "Wave_Started:5",
        "Category": "default",
        "Value": 3000,
        "Shared": false,
        "Expires": false
    },
    {
        "ContributionId": "Wave_Started:6",
        "Category": "default",
        "Value": 5000,
        "Shared": false,
        "Expires": false
    },
    {
        "ContributionId": "Wave_Started:7",
        "Category": "default",
        "Value": 7000,
        "Shared": false,
        "Expires": false
    },
    {
        "ContributionId": "Wave_Started:8",
        "Category": "default",
        "Value": 12000,
        "Shared": false,
        "Expires": false
    }
]