[
    {
        "EventID": "7404_0101_devworldredkillwitheredquest_success",
        "Level": 1,
        "CreatureType": "Quest",
        "UniversalExpAmount": 75,
        "CurrencyReward": 1517,
        "ItemReward": "QuestRewardArmorT2",
        "GearScoreRange": 0,
        "TerritoryStanding": 175,
        "EmitTelemetry": true,
        "AzothReward": 0,
        "AzothRewardChance": 1
    },
    {
        "EventID": "7405_0101_devworldredgetfarmlootquest_success",
        "Level": 1,
        "CreatureType": "Quest",
        "UniversalExpAmount": 75,
        "CurrencyReward": 1517,
        "ItemReward": "2hWarhammerDropT2",
        "GearScoreRange": 100,
        "TerritoryStanding": 100,
        "EmitTelemetry": true,
        "AzothReward": 0,
        "AzothRewardChance": 1
    },
    {
        "EventID": "74_0101_devworldreddefendobjectquest_success",
        "Level": 1,
        "CreatureType": "Quest",
        "UniversalExpAmount": 75,
        "CurrencyReward": 1517,
        "ItemReward": "2hWarhammerDropT2",
        "GearScoreRange": 100,
        "TerritoryStanding": 100,
        "EmitTelemetry": true,
        "AzothReward": 0,
        "AzothRewardChance": 1
    },
    {
        "EventID": "74_0101_devworldreddefendobjectquest_interact",
        "Level": 1,
        "CreatureType": "Quest-",
        "UniversalExpAmount": 0,
        "CurrencyReward": 0,
        "GearScoreRange": 0,
        "TerritoryStanding": 0,
        "EmitTelemetry": true,
        "AzothReward": 0,
        "AzothRewardChance": 0
    },
    {
        "EventID": "74_0101_devworldreddefendobjectquest_participate",
        "Level": 1,
        "CreatureType": "Quest-",
        "UniversalExpAmount": 0,
        "CurrencyReward": 0,
        "GearScoreRange": 0,
        "TerritoryStanding": 0,
        "EmitTelemetry": true,
        "AzothReward": 0,
        "AzothRewardChance": 0
    }
]